datepulator/__init__.py
datepulator/core.py
datepulator-0.1.1.dist-info/LICENSE
datepulator-0.1.1.dist-info/METADATA
datepulator-0.1.1.dist-info/WHEEL
datepulator-0.1.1.dist-info/top_level.txt
datepulator-0.1.1.dist-info/RECORD
