Metadata-Version: 2.1
Name: datepulator
Version: 0.1.1
Summary: A powerful Python library for date manipulation and formatting
Home-page: https://github.com/yourusername/datepulator
Author: Ashutosh Bele
Author-email: Ashutosh Bele <your.email@example.com>
License: MIT License
Project-URL: Homepage, https://github.com/yourusername/datepulator
Project-URL: Repository, https://github.com/yourusername/datepulator.git
Project-URL: Documentation, https://github.com/yourusername/datepulator#readme
Project-URL: Bug Tracker, https://github.com/yourusername/datepulator/issues
Keywords: date,time,manipulation,formatting,timezone,business days
Classifier: Development Status :: 3 - Alpha
Classifier: Intended Audience :: Developers
Classifier: License :: OSI Approved :: MIT License
Classifier: Operating System :: OS Independent
Classifier: Programming Language :: Python :: 3
Classifier: Programming Language :: Python :: 3.7
Classifier: Programming Language :: Python :: 3.8
Classifier: Programming Language :: Python :: 3.9
Classifier: Programming Language :: Python :: 3.10
Requires-Python: >=3.7
License-File: LICENSE
Requires-Dist: pandas>=1.0.0
Requires-Dist: python-dateutil>=2.8.0
Requires-Dist: pytz>=2021.1
